LICENCE.md
MANIFEST.in
README.rst
setup.py
django_errordite/__init__.py
django_errordite/handlers.py
django_errordite.egg-info/PKG-INFO
django_errordite.egg-info/SOURCES.txt
django_errordite.egg-info/dependency_links.txt
django_errordite.egg-info/requires.txt
django_errordite.egg-info/top_level.txt