Metadata-Version: 1.1
Name: django-errordite
Version: 0.8
Summary: Errordite exception logging for Django.
Home-page: https://github.com/hugorodgerbrown/django-errordite
Author: Hugo Rodger-Brown
Author-email: hugo@rodger-brown.com
License: Copyright (c) 2013, Hugo Rodger-Brown
